shared_msg/__init__.py
shared_msg/app.py
shared_msg/conf.py
shared_msg/managers.py
shared_msg/models.py
shared_msg/router.py
shared_msg/message/__init__.py
shared_msg/message/services/__init__.py
shared_msg/message/services/twilio_service.py
shared_msg/message/utils/__init__.py
shared_msg/message/utils/build_email_message.py
shared_msg/message/utils/build_sms_message.py
shared_msg/message/utils/build_whatsapp_message.py
shared_msg/message/utils/send_message.py
shared_msg/mixins/__init__.py
shared_msg/mixins/contact.py
maquinaweb_shared_msg-0.1.10.dist-info/METADATA
maquinaweb_shared_msg-0.1.10.dist-info/WHEEL
maquinaweb_shared_msg-0.1.10.dist-info/top_level.txt
maquinaweb_shared_msg-0.1.10.dist-info/RECORD
