Metadata-Version: 2.4
Name: maquinaweb-shared-msg
Version: 0.1.10
Summary: Models and Functions for to send messages to contacts.
Author-email: Seu Nome <seuemail@dominio.com>
License: MIT
Project-URL: Homepage, https://github.com/maquinaweb/maquinaweb-shared-msg
Project-URL: Repository, https://github.com/maquinaweb/maquinaweb-shared-msg
Project-URL: Issues, https://github.com/maquinaweb/maquinaweb-shared-msg/issues
Keywords: django,msg,models,shared
Classifier: Framework :: Django
Classifier: Programming Language :: Python :: 3
Classifier: License :: OSI Approved :: MIT License
Classifier: Operating System :: OS Independent
Requires-Python: >=3.8
Requires-Dist: django>=5
Requires-Dist: django-storages>=1.14.6
Requires-Dist: djangorestframework>=3
Requires-Dist: pyyaml>=6.0.3
Requires-Dist: setuptools>=70
Requires-Dist: twilio>=9.8.8
Requires-Dist: zappa>=0.61.2
Dynamic: requires-python
